agentcompiler/__init__.py
agentcompiler/agent.py
agentcompiler-0.0.0.dist-info/licenses/LICENSE
agentcompiler-0.0.0.dist-info/METADATA
agentcompiler-0.0.0.dist-info/WHEEL
agentcompiler-0.0.0.dist-info/top_level.txt
agentcompiler-0.0.0.dist-info/RECORD
