Metadata-Version: 2.4
Name: AgentCompiler
Version: 0.0.0
Summary: A Compiler for Agent Workflow
License:                                  Apache License
Requires-Python: >=3.8
License-File: LICENSE
Dynamic: license-file
